{
    "title": "Updates in Hoogii !",
    "version": "1.0.7",
    "subtitle": "Version 0.0.7",
    "contents": [
        {
            "title": "Hoogii now supports HashgreenSwap v0.1(testnet)!",
            "description": "You can now use Hoogii to connect Hashgreenswap v0.1 and swap or stake on testnet!"
        },
        {
            "title": "Optimize user interface and experience",
            "description": "Optimize the user experience when importing tokens, and add update notifications."
        }
    ]
}
